LICENSE.txt
MANIFEST.in
README.md
README.rst
setup.cfg
setup.py
rdmcl/__init__.py
rdmcl/compare_homolog_groups.py
rdmcl/group_by_cluster.py
rdmcl/helpers.py
rdmcl/homolog_tree_builder.py
rdmcl/install.py
rdmcl/launch_worker.py
rdmcl/mcmcmc.py
rdmcl/monitor_dbs.py
rdmcl/rdmcl.py
rdmcl/reset_workers.py
rdmcl.egg-info/PKG-INFO
rdmcl.egg-info/SOURCES.txt
rdmcl.egg-info/dependency_links.txt
rdmcl.egg-info/entry_points.txt
rdmcl.egg-info/not-zip-safe
rdmcl.egg-info/requires.txt
rdmcl.egg-info/top_level.txt