Metadata-Version: 1.1
Name: rdmcl
Version: 1.1.0
Summary: RDMCL recursively clusters groups of homologous sequences into orthogroups.
Home-page: https://github.com/biologyguy/RD-MCL
Author: Stephen Bond
Author-email: steve.bond@nih.gov
License: Public Domain
Keywords: computational biology,bioinformatics,orthogroup,ortholog,biology,Markov clustering,MCL
Platform: UNKNOWN
Classifier: Development Status :: 5 - Production/Stable
Classifier: Topic :: Scientific/Engineering
Classifier: Topic :: Scientific/Engineering :: Bio-Informatics
Classifier: Topic :: Software Development :: Libraries :: Python Modules
Classifier: Intended Audience :: Science/Research
Classifier: Operating System :: MacOS :: MacOS X
Classifier: Operating System :: POSIX :: Linux
Classifier: Programming Language :: Python :: 3
Classifier: Programming Language :: Python :: 3.4
Classifier: Programming Language :: Python :: 3.5
Classifier: Programming Language :: Python :: 3 :: Only
Classifier: License :: Public Domain
Classifier: Natural Language :: English
Classifier: Environment :: Console
